rils_rols_cpp.cp311-win_amd64.pyd
rils_rols/__init__.py
rils_rols/rils_rols.py
rils_rols/rils_rols_ensemble.py
rils_rols/utils.py
rils_rols-1.6.7.dist-info/LICENSE
rils_rols-1.6.7.dist-info/METADATA
rils_rols-1.6.7.dist-info/WHEEL
rils_rols-1.6.7.dist-info/top_level.txt
rils_rols-1.6.7.dist-info/RECORD
